databind/_version/__init__.py
databind2-4.2.2.dist-info/WHEEL
databind2-4.2.2.dist-info/METADATA
databind2-4.2.2.dist-info/RECORD
