Metadata-Version: 2.1
Name: databind2
Version: 4.2.2
Summary: Databind is a library inspired by jackson-databind to de-/serialize Python dataclasses. The `databind` package will install the full suite of databind packages. Compatible with Python 3.7 and newer.
License: MIT
Author: Niklas Rosenstein
Author-email: rosensteinniklas@gmail.com
Requires-Python: >=3.6.3,<4.0.0
Classifier: License :: OSI Approved :: MIT License
Classifier: Programming Language :: Python :: 3
Classifier: Programming Language :: Python :: 3.7
Classifier: Programming Language :: Python :: 3.8
Classifier: Programming Language :: Python :: 3.9
Classifier: Programming Language :: Python :: 3.10
Classifier: Programming Language :: Python :: 3.11
Requires-Dist: databind-core2 (>=4.2.2,<5.0.0)
Requires-Dist: databind-json2 (>=4.2.2,<5.0.0)
